[
  {
    "chain-name": "cytonic-l2-testnet",
    "parent-chain-id": 52225,
    "parent-chain-is-arbitrum": false,
    "sequencer-url": "",
    "secondary-forwarding-target": "",
    "feed-url": "",
    "secondary-feed-url": "",
    "das-index-url": "",
    "has-genesis-state": false,
    "chain-config": {
      "chainId": 52226,
      "homesteadBlock": 0,
      "daoForkSupport": true,
      "eip150Block": 0,
      "eip150Hash": "0x0000000000000000000000000000000000000000000000000000000000000000",
      "eip155Block": 0,
      "eip158Block": 0,
      "byzantiumBlock": 0,
      "constantinopleBlock": 0,
      "petersburgBlock": 0,
      "istanbulBlock": 0,
      "muirGlacierBlock": 0,
      "berlinBlock": 0,
      "londonBlock": 0,
      "clique": {
        "period": 0,
        "epoch": 0
      },
      "arbitrum": {
        "EnableArbOS": true,
        "AllowDebugPrecompiles": true,
        "DataAvailabilityCommittee": false,
        "InitialArbOSVersion": 32,
        "InitialChainOwner": "0x4832AF44dC71309e16243AFC3745Fc61459ed2d6",
        "GenesisBlockNum": 0
      }
    },
    "rollup": {
      "bridge": "0xBEb2424288B0be8c8E93b1D3Ba0193468841e5e3",
      "inbox": "0xc8f8C393A257aCb0b59112250a5b73E82E92478e",
      "sequencer-inbox": "0x938a60Ea989E1D0ED5d1A3F60955F2B5cAADac92",
      "deployed-at": 1394795,
      "rollup": "0x1D6058e61095a5208F15f3968Fe60ea493Eb705A",
      "native-token": "0x0000000000000000000000000000000000000000",
      "upgrade-executor": "0x59abB33aB8EDE3be0c64a9ddDa8961ceAC275e07",
      "validator-utils": "0xDFe5574e08d94962C45Ab68Aa2a74BF8aF50E3f2",
      "validator-wallet-creator": "0x10C4C5a34b422078bDB2f6a54267bFb710d5Bfe6"
    }
  }
]